src/mux_regdst.v
module mux_regdst (
    input wire [4:0] rt,
    input wire [4:0] rd,
    input wire RegDst,
    output wire [4:0] RegDstOut
);
    assign RegDstOut = RegDst ? rd : rt;
endmodule

src/mux_memtoreg.v
module mux_memtoreg (
    input wire [31:0] ALUResult, MemData,
    input wire MemToReg,
    output reg [31:0] WriteData
);
    always @(*) begin
        if (MemToReg) 
            WriteData = MemData;
        else 
            WriteData = ALUResult;
    end
endmodule

src/mux_alu_src.v
module mux_alu_src(
    input wire [31:0] reg_data,    // Valor ReadData2
    input wire [31:0] imm_ext,     // Valor imediato 
    input wire ALUSrc,             // 0 = registrador, 1 = imediato
    output wire [31:0] mux_out     
);
    always @(*) begin
    if (ALUSrc)
        mux_out = imm_ext;
    else
        mux_out = reg_data;
    end
endmodule

src/d_mem.v
module d_mem #(
    parameter SIZE = 1024       
)(
    input wire [31:0] Address,   
    input wire [31:0] WriteData, 
    input wire MemWrite,         
    input wire MemRead,          
    output reg [31:0] ReadData   
);

    always @(*) begin
        if (MemRead) begin
            ReadData = memory[Address >> 2]; 
        end else begin
            ReadData = 32'bz; // Alta impedância quando não estiver lendo
        end
    end

    always @(*) begin
        if (MemWrite) begin
            memory[Address >> 2] = WriteData;
        end
    end

endmodule

src/ula.v
module ula (
    input wire [31:0] In1,    
    input wire [31:0] In2,
    input wire [3:0] OP,
    output wire [31:0] result,
    output wire Zero_flag
);
    always @(*) begin
        case (OP)
            4'b0001: result = In1 + In2;                        // 1. Soma
            4'b0010: result = In1 - In2;                        // 2. Subtração
            4'b0011: result = In1 & In2;                        // 3. AND bit a bit
            4'b0100: result = In1 | In2;                        // 4. OR bit a bit
            4'b0101: result = In1 ^ In2;                        // 5. XOR bit a bit
            4'b0110: result = ~In1;                             // 6. NOT bit a bit (aplicado apenas a In1)
            4'b0111: result = In1 << In2;                       // 7. Deslocamento lógico à esquerda
            4'b1000: result = In1 >> In2;                       // 8. Deslocamento lógico à direita
            4'b1001: result = $signed(In1) >>> In2;             // 9. Deslocamento aritmético à direita
            4'b1010: result = (In1 < In2) ? 1 : 0;              // 10. Set Less Than (SLT)
            4'b1011: result = (In1 < In2) ? 1 : 0;              // 11. Set Less Than Unsigned (SLTU)
            4'b1100: result = In1 * In2;                        // 12. Multiplicação (se suportada)
            4'b1101: result = (In2 != 0) ? In1 / In2 : 32'b0;   // 13. Divisão (evita divisão por zero)
            4'b1110: result = In1 + 1;                          // 14. Incremento
            4'b1111: result = In1 - 1;                          // 15. Decremento
            default: result = 32'b0;                            // Caso padrão (operação inválida retorna 0)
        endcase
    
        if (result == 32'b0) begin                              // 16. Comparação de igualdade (Zero_flag)
            Zero_flag = 1'b1;       // Ativa se for 0
        end else begin
            Zero_flag = 1'b0;       // desativa
        end
            Zero_flag = (result == 32'b0) ? 1'b1 : 1'b0;            
        end
    
endmodule

src/ula_ctrl.v
module ula_ctrl(
    input wire [1;0] ALUOp,
    input wire [5:0] func,
    output wire [3:0] OP
);
    always @(*) begin
        case(ALUOp)
            2'b00: OP = 4'b0010;    // Soma (usado por LW, SW)
            2'b01: OP = 4'b0110;    // Subtração (usado por BEQ)
            2'b10: begin            // Instruções do tipo R
                case(func)
                    6'b100000: OP = 4'b0001; // ADD
                    6'b100010: OP = 4'b0010; // SUB
                    6'b100100: OP = 4'b0011; // AND
                    6'b100101: OP = 4'b0100; // OR
                    6'b100110: OP = 4'b0101; // XOR
                    6'b100111: OP = 4'b0110; // NOT (somente In1)
                    6'b000000: OP = 4'b0111; // SLL (Shift Left Logical)
                    6'b000010: OP = 4'b1000; // SRL (Shift Right Logical)
                    6'b000011: OP = 4'b1001; // SRA (Shift Right Arithmetic)
                    6'b101010: OP = 4'b1010; // SLT (Set Less Than)
                    6'b101011: OP = 4'b1011; // SLTU (Set Less Than Unsigned)
                    6'b011000: OP = 4'b1100; // MULT (Multiplicação)
                    6'b011001: OP = 4'b1100; // MULTU (Multiplicação sem sinal) - mesmo código
                    6'b011010: OP = 4'b1101; // DIV (Divisão)
                    6'b011011: OP = 4'b1101; // DIVU (Divisão sem sinal) - mesmo código
                    6'b100001: OP = 4'b1110; // ADDI (Incremento de 1)
                    6'b100011: OP = 4'b1111; // SUBI (Decremento de 1)
                    default: OP = 4'b0000;   // Caso inválido
                endcase
            end
            default: OP = 4'b1111;  // Operação invalida
        endcase
    end

endmodule

src/control.v
module control (
    input [5:0] opcode,      // Opcode da instrução
    input [5:0] func,        // Campo func (para instruções tipo R)
    output reg RegDst,       // Seleciona rd (1) ou rt (0) como destino
    output reg ALUSrc,       // Seleciona imediato (1) ou registrador (0)
    output reg MemtoReg,     // Seleciona memória (1) ou ULA (0) para WriteData
    output reg RegWrite,     // Habilita escrita no regfile
    output reg MemRead,      // Habilita leitura da memória de dados
    output reg MemWrite,     // Habilita escrita na memória de dados
    output reg Branch,       // Habilita desvio condicional (beq/bne)
    output reg [1:0] ALUOp,  // Define operação da ULA (00: ADD, 01: SUB, 10: func, 11: lógica)
    output reg Jump,         // Habilita salto incondicional (j/jal)
    output reg Jal,          // Indica instrução jal (escreve PC+8 em $31)
    output reg Jr,           // Habilita salto por registrador (jr)
    output reg ExtOp         // Extensão de sinal (1) ou zero (0)
);

always @(*) begin
    // Valores padrão para evitar latches
    RegDst = 0;
    ALUSrc = 0;
    MemtoReg = 0;
    RegWrite =0; 
    MemRead = 0; 
    MemWrite =0; 
    Branch = 0;
    ALUOp = 0;
    Jump = 0;
    Jal = 0;
    Jr = 0;
    ExtOp = 0;

    case (opcode)
        // Instruções Tipo R (opcode = 0)
        6'b000000: begin
            RegDst = 1;      // Destino é rd
            RegWrite = 1;    // Habilita escrita
            ALUOp = 2'b10;   // Operação definida pelo campo func

            // Trata instrução jr (func = 8)
            if (func == 6'b001000) begin
                Jr = 1;     // Ativa sinal Jr
                RegWrite = 0; // Não escreve no regfile
            end
        end

        // Instruções Tipo I
        6'b001000: begin // addi
            ALUSrc = 1;
            RegWrite = 1;
            ExtOp = 1;      // Extensão de sinal
            ALUOp = 2'b00;  // ADD
        end

        6'b001100: begin // andi
            ALUSrc = 1;
            RegWrite = 1;
            ALUOp = 2'b11;  // Operação lógica (AND)
            ExtOp = 0;      // Extensão zero
        end

        6'b001101: begin // ori
            ALUSrc = 1;
            RegWrite = 1;
            ALUOp = 2'b11;  // Operação lógica (OR)
            ExtOp = 0;
        end

        6'b001110: begin // xori
            ALUSrc = 1;
            RegWrite = 1;
            ALUOp = 2'b11;  // Operação lógica (XOR)
            ExtOp = 0;
        end

        6'b001010: begin // slti (signed)
            ALUSrc = 1;
            RegWrite = 1;
            ALUOp = 2'b01;  // SLT
            ExtOp = 1;
        end

        6'b001011: begin // sltiu (unsigned)
            ALUSrc = 1;
            RegWrite = 1;
            ALUOp = 2'b01;  // SLTU
            ExtOp = 1;
        end

        6'b001111: begin // lui
            ALUSrc = 1;
            RegWrite = 1;
            ALUOp = 2'b00;  // Shift left 16 bits (tratado na ULA)
            ExtOp = 0;      // Não importa (imediado já está nos 16 bits superiores)
        end

        6'b000100: begin // beq
            Branch = 1;
            ALUOp = 2'b01;  // SUB (para comparação)
            ExtOp = 1;
        end

        6'b000101: begin // bne
            Branch = 1;
            ALUOp = 2'b01;  // SUB (para comparação)
            ExtOp = 1;
        end

        6'b100011: begin // lw
            ALUSrc = 1;
            MemtoReg = 1;   // Dado vem da memória
            RegWrite = 1;
            MemRead = 1;    // Habilita leitura da memória
            ExtOp = 1;
            ALUOp = 2'b00;  // ADD (cálculo do endereço)
        end

        6'b101011: begin // sw
            ALUSrc = 1;
            MemWrite = 1;   // Habilita escrita na memória
            ExtOp = 1;
            ALUOp = 2'b00;  // ADD (cálculo do endereço)
        end

        // Instruções Tipo J
        6'b000010: begin // j
            Jump = 1;
        end

        6'b000011: begin // jal
            Jump = 1;
            Jal = 1;
            RegWrite = 1;   // Escreve PC+8 em $31
        end

        default: ; // Instrução inválida (NOP)
    endcase
end

endmodule

src/regfile.v
module regfile(

    input wire [4:0] ReadAddr1,
    input wire [4:0] ReadAddr2, 
    input wire clock,
    input wire [4:0] WriteAddr,         //endereço do registrador a ser escrito
    input wire [31:0] WriteData,
    input wire RegWrite, 
    input wire Reset
    output wire [31:0] ReadData1,
    output wire [31:0] ReadData2
);
    
    reg [31:0] registradores[31:0]; // vetor de 32 registradores de 32 bits 
    interger i; // ponteiro para os registradores

    //dados lidos
    assign ReadData1 = regs[ReadAddr1];
    assign ReadData2 = regs[ReadAddr2];

    // subida do clock ou reset = 1
    always @(posedge Clock or posedge Reset) begin

        // verifica se foi o reset
        if(Reset) begin

            //Reseta todos os registradores
            for (i = 0; i < 32; i = i + 1)
                regs[i] <= 32'b0;
        
        // Caso tenha sido na subida do clock
        end else begin

        // verifica se RegWrite = 1, e se não é o $0
        if (RegWrite && (WriteAddr != 5'd0))
        
            regs[WriteAddr] <= WriteData;       //escrita no registrador desejado
        end
    end
endmodule

src/i_mem.v
module i_mem (
    input wire [31:0] address,
    output reg [31:0] i_out
);
    reg [31:0] memory [0:63]; // Memória de 64 palavras de 32 bits

    initial begin
        $readmemb("instructions.list", memory); // Lê o arquivo binário linha por linha
    end

    always @(address) begin
        i_out = memory[address >> 2]; // Alinhamento com 32 bits
    end
endmodule

src/pc.v
module pc (
    input wire clock,
    input wire reset,
    input wire [31:0] nextPC,
    output reg [31:0] PC
);

    always @(posedge clock or posedge reset) begin
        if (reset) begin
            PC <= 32'b0; // Resetar o PC para 0
        end else begin
            PC <= nextPC; // Atualizar o PC com o próximo valor
        end
    end

endmodule

src/top_level.v
`timescale 1ns/1ps

module top_level (
    input wire clock,
    input wire reset,
    output wire [31:0] PC_out,
    output wire [31:0] ULA_out,
    output wire [31:0] MemData_out,
    output wire [31:0] instruction_out // Adicione esta linha para exportar a instrução
);

    // Sinais internos
    wire [31:0] PC, nextPC, instruction, ReadData1, ReadData2, ALUResult, MemData, WriteData;
    wire [31:0] SignExtImm, ALUSrcB, BranchAddr, JumpAddr;
    wire [4:0] WriteReg;
    wire [3:0] ALUControl;
    wire [1:0] ALUOp;
    wire RegDst, ALUSrc, MemtoReg, RegWrite, MemRead, MemWrite, Branch, Jump, Jal, Jr, ExtOp, Zero;

    // Instância do PC
    pc pc_inst (
        .clock(clock),
        .reset(reset),
        .nextPC(nextPC),
        .PC(PC)
    );

    // Instância da memória de instruções
    i_mem i_mem_inst (
        .address(PC),
        .i_out(instruction)
    );

    // Instância do banco de registradores
    regfile regfile_inst (
        .ReadAddr1(instruction[25:21]),
        .ReadAddr2(instruction[20:16]),
        .clock(clock),
        .WriteAddr(WriteReg),
        .WriteData(WriteData),
        .RegWrite(RegWrite),
        .Reset(reset),
        .ReadData1(ReadData1),
        .ReadData2(ReadData2)
    );

    // Instância da unidade de controle
    control control_inst (
        .opcode(instruction[31:26]),
        .func(instruction[5:0]),
        .RegDst(RegDst),
        .ALUSrc(ALUSrc),
        .MemtoReg(MemtoReg),
        .RegWrite(RegWrite),
        .MemRead(MemRead),
        .MemWrite(MemWrite),
        .Branch(Branch),
        .ALUOp(ALUOp),
        .Jump(Jump),
        .Jal(Jal),
        .Jr(Jr),
        .ExtOp(ExtOp)
    );

    // Instância da unidade de controle da ULA
    ula_ctrl ula_ctrl_inst (
        .ALUOp(ALUOp),
        .func(instruction[5:0]),
        .OP(ALUControl)
    );

    // Instância da ULA
    ula ula_inst (
        .In1(ReadData1),
        .In2(ALUSrcB),
        .OP(ALUControl),
        .result(ALUResult),
        .Zero_flag(Zero)
    );

    // Instância da memória de dados
    d_mem d_mem_inst (
        .Address(ALUResult),
        .WriteData(ReadData2),
        .MemWrite(MemWrite),
        .MemRead(MemRead),
        .ReadData(MemData)
    );

    // Multiplexador para ALUSrc
    mux_alu_src mux_alu_src_inst (
        .reg_data(ReadData2),
        .imm_ext(SignExtImm),
        .ALUSrc(ALUSrc),
        .mux_out(ALUSrcB)
    );

    // Multiplexador para MemtoReg
    mux_memtoreg mux_memtoreg_inst (
        .ALUResult(ALUResult),
        .MemData(MemData),
        .MemToReg(MemtoReg),
        .WriteData(WriteData)
    );

    // Multiplexador para RegDst
    mux_regdst mux_regdst_inst (
        .rt(instruction[20:16]),
        .rd(instruction[15:11]),
        .RegDst(RegDst),
        .RegDstOut(WriteReg)
    );

    // Extensão de sinal
    assign SignExtImm = ExtOp ? {{16{instruction[15]}}, instruction[15:0]} : {16'b0, instruction[15:0]};

    // Calcular endereço de desvio
    assign BranchAddr = PC + (SignExtImm << 2);

    // Calcular endereço de salto
    assign JumpAddr = {PC[31:28], instruction[25:0], 2'b00};

    // Multiplexador para PCSrc
    assign nextPC = (Jr) ? ReadData1 :
                    (Jump) ? JumpAddr :
                    (Branch && Zero) ? BranchAddr :
                    PC + 4;

    // Saídas
    assign PC_out = PC;
    assign ULA_out = ALUResult;
    assign MemData_out = MemData;
    assign instruction_out = instruction; // Adicione esta linha para exportar a instrução

endmodule

src/top_level_tb.v
`timescale 1ns/1ps

module top_level_tb;

    reg clock;
    reg reset;
    wire [31:0] PC_out;
    wire [31:0] ULA_out;
    wire [31:0] MemData_out;
    wire [31:0] instruction_out; // Adicione esta linha para monitorar a instrução

    // Instância do módulo top_level
    top_level uut (
        .clock(clock),
        .reset(reset),
        .PC_out(PC_out),
        .ULA_out(ULA_out),
        .MemData_out(MemData_out),
        .instruction_out(instruction_out) // Adicione esta linha para conectar a instrução
    );

    // Gerador de clock
    initial begin
        clock = 0;
        forever #5 clock = ~clock; // Clock com período de 10 unidades de tempo
    end

    // Sequência de reset e simulação
    initial begin
        // Inicialização
        reset = 1;
        #10;
        reset = 0;

        // Tempo de simulação
        #1000;
        $finish;
    end

    // Monitoramento
    initial begin
        $monitor("Time: %0t | PC: %h | Instruction: %b | ALUResult: %d | MemData: %h", $time, PC_out, instruction_out, ULA_out, MemData_out);
    end

    // Gerar arquivo de dump para visualização no GTKWave
    initial begin
        $dumpfile("top_level_tb.vcd");
        $dumpvars(0, top_level_tb);
    end

endmodule

src/top_level_tb.vcd
$date
	Tue Mar 11 13:20:14 2025
$end
$version
	Icarus Verilog
$end
$timescale
	1ps
$end
$scope module top_level_tb $end
$var wire 32 ! instruction_out [31:0] $end
$var wire 32 " ULA_out [31:0] $end
$var wire 32 # PC_out [31:0] $end
$var wire 32 $ MemData_out [31:0] $end
$var reg 1 % clock $end
$var reg 1 & reset $end
$scope module uut $end
$var wire 32 ' MemData_out [31:0] $end
$var wire 32 ( PC_out [31:0] $end
$var wire 32 ) ULA_out [31:0] $end
$var wire 1 % clock $end
$var wire 32 * instruction_out [31:0] $end
$var wire 1 & reset $end
$var wire 32 + nextPC [31:0] $end
$var wire 32 , instruction [31:0] $end
$var wire 1 - Zero $end
$var wire 5 . WriteReg [4:0] $end
$var wire 32 / WriteData [31:0] $end
$var wire 32 0 SignExtImm [31:0] $end
$var wire 1 1 RegWrite $end
$var wire 1 2 RegDst $end
$var wire 32 3 ReadData2 [31:0] $end
$var wire 32 4 ReadData1 [31:0] $end
$var wire 32 5 PC [31:0] $end
$var wire 1 6 MemtoReg $end
$var wire 1 7 MemWrite $end
$var wire 1 8 MemRead $end
$var wire 32 9 MemData [31:0] $end
$var wire 32 : JumpAddr [31:0] $end
$var wire 1 ; Jump $end
$var wire 1 < Jr $end
$var wire 1 = Jal $end
$var wire 1 > ExtOp $end
$var wire 32 ? BranchAddr [31:0] $end
$var wire 1 @ Branch $end
$var wire 32 A ALUSrcB [31:0] $end
$var wire 1 B ALUSrc $end
$var wire 32 C ALUResult [31:0] $end
$var wire 2 D ALUOp [1:0] $end
$var wire 4 E ALUControl [3:0] $end
$scope module control_inst $end
$var wire 6 F func [5:0] $end
$var wire 6 G opcode [5:0] $end
$var reg 2 H ALUOp [1:0] $end
$var reg 1 B ALUSrc $end
$var reg 1 @ Branch $end
$var reg 1 > ExtOp $end
$var reg 1 = Jal $end
$var reg 1 < Jr $end
$var reg 1 ; Jump $end
$var reg 1 8 MemRead $end
$var reg 1 7 MemWrite $end
$var reg 1 6 MemtoReg $end
$var reg 1 2 RegDst $end
$var reg 1 1 RegWrite $end
$upscope $end
$scope module d_mem_inst $end
$var wire 1 8 MemRead $end
$var wire 1 7 MemWrite $end
$var wire 32 I WriteData [31:0] $end
$var wire 32 J Address [31:0] $end
$var reg 32 K ReadData [31:0] $end
$upscope $end
$scope module i_mem_inst $end
$var wire 32 L address [31:0] $end
$var reg 32 M i_out [31:0] $end
$upscope $end
$scope module mux_alu_src_inst $end
$var wire 1 B ALUSrc $end
$var wire 32 N imm_ext [31:0] $end
$var wire 32 O reg_data [31:0] $end
$var reg 32 P mux_out [31:0] $end
$upscope $end
$scope module mux_memtoreg_inst $end
$var wire 32 Q MemData [31:0] $end
$var wire 1 6 MemToReg $end
$var wire 32 R WriteData [31:0] $end
$var wire 32 S ALUResult [31:0] $end
$upscope $end
$scope module mux_regdst_inst $end
$var wire 1 2 RegDst $end
$var wire 5 T rd [4:0] $end
$var wire 5 U rt [4:0] $end
$var wire 5 V RegDstOut [4:0] $end
$upscope $end
$scope module pc_inst $end
$var wire 1 % clock $end
$var wire 32 W nextPC [31:0] $end
$var wire 1 & reset $end
$var reg 32 X PC [31:0] $end
$upscope $end
$scope module regfile_inst $end
$var wire 5 Y ReadAddr1 [4:0] $end
$var wire 5 Z ReadAddr2 [4:0] $end
$var wire 1 1 RegWrite $end
$var wire 1 & Reset $end
$var wire 5 [ WriteAddr [4:0] $end
$var wire 32 \ WriteData [31:0] $end
$var wire 1 % clock $end
$var reg 32 ] ReadData1 [31:0] $end
$var reg 32 ^ ReadData2 [31:0] $end
$var integer 32 _ i [31:0] $end
$upscope $end
$scope module ula_ctrl_inst $end
$var wire 2 ` ALUOp [1:0] $end
$var wire 6 a func [5:0] $end
$var reg 4 b OP [3:0] $end
$upscope $end
$scope module ula_inst $end
$var wire 32 c In1 [31:0] $end
$var wire 32 d In2 [31:0] $end
$var wire 4 e OP [3:0] $end
$var reg 1 - Zero_flag $end
$var reg 32 f result [31:0] $end
$upscope $end
$upscope $end
$upscope $end
$enddefinitions $end
$comment Show the parameter values. $end
$dumpall
$end
#0
$dumpvars
b11111111111111111111111111110001 f
b10 e
b1111 d
b0 c
b10 b
b1111 a
b0 `
b100000 _
b0 ^
b0 ]
b11111111111111111111111111110001 \
b1 [
b1 Z
b0 Y
b0 X
b100 W
b1 V
b1 U
b0 T
b11111111111111111111111111110001 S
b11111111111111111111111111110001 R
bx Q
b1111 P
b0 O
b1111 N
b111100000000010000000000001111 M
b0 L
bx K
b11111111111111111111111111110001 J
b0 I
b0 H
b1111 G
b1111 F
b10 E
b0 D
b11111111111111111111111111110001 C
1B
b1111 A
0@
b111100 ?
0>
0=
0<
0;
b1000000000000111100 :
bx 9
08
07
06
b0 5
b0 4
b0 3
02
11
b1111 0
b11111111111111111111111111110001 /
b1 .
0-
b111100000000010000000000001111 ,
b100 +
b111100000000010000000000001111 *
b11111111111111111111111111110001 )
b0 (
bx '
1&
0%
bx $
b0 #
b11111111111111111111111111110001 "
b111100000000010000000000001111 !
$end
#5000
b100000 _
1%
#10000
0%
0&
#15000
b11111111111111111111111111110000 /
b11111111111111111111111111110000 R
b11111111111111111111111111110000 \
b1010000000000000 A
b1010000000000000 P
b1010000000000000 d
b11111111111111111111111111110000 "
b11111111111111111111111111110000 )
b11111111111111111111111111110000 C
b11111111111111111111111111110000 J
b11111111111111111111111111110000 S
b11111111111111111111111111110000 f
b1000 +
b1000 W
b1010000000000000 0
b1010000000000000 N
b1111 E
b1111 b
b1111 e
b11 D
b11 H
b11 `
11
1B
b11111111111111111111111111110001 4
b11111111111111111111111111110001 ]
b11111111111111111111111111110001 c
b100001101000000000000000 :
b10100 T
b0 a
b0 F
b1101 G
b1 Y
b110100001000011010000000000000 !
b110100001000011010000000000000 *
b110100001000011010000000000000 ,
b110100001000011010000000000000 M
b11111111111111111111111111110001 3
b11111111111111111111111111110001 I
b11111111111111111111111111110001 O
b11111111111111111111111111110001 ^
b101000000000000100 ?
b100 #
b100 (
b100 5
b100 L
b100 X
1%
#20000
0%
#25000
b11001 .
b11001 V
b11001 [
b11111111111111111111111111110000 A
b11111111111111111111111111110000 P
b11111111111111111111111111110000 d
b11111111111111111111111111110000 /
b11111111111111111111111111110000 R
b11111111111111111111111111110000 \
b1100 +
b1100 W
b1100100000100000 0
b1100100000100000 N
b1 E
b1 b
b1 e
12
b10 D
b10 H
b10 `
11
0B
b11111111111111111111111111110000 "
b11111111111111111111111111110000 )
b11111111111111111111111111110000 C
b11111111111111111111111111110000 J
b11111111111111111111111111110000 S
b11111111111111111111111111110000 f
b1110010000010000000 :
b11001 T
b100000 a
b100000 F
b0 G
b0 Y
b11111111111111111111111111110000 3
b11111111111111111111111111110000 I
b11111111111111111111111111110000 O
b11111111111111111111111111110000 ^
b0 4
b0 ]
b0 c
b11100100000100000 !
b11100100000100000 *
b11100100000100000 ,
b11100100000100000 M
b110010000010001000 ?
b1000 #
b1000 (
b1000 5
b1000 L
b1000 X
1%
#30000
0%
#35000
b11111111111111111111111111101111 /
b11111111111111111111111111101111 R
b11111111111111111111111111101111 \
b1 A
b1 P
b1 d
0-
b11111111111111111111111111101111 "
b11111111111111111111111111101111 )
b11111111111111111111111111101111 C
b11111111111111111111111111101111 J
b11111111111111111111111111101111 S
b11111111111111111111111111101111 f
b10000 +
b10000 W
b1 0
b1 N
b10 E
b10 b
b10 e
1>
1B
b0 D
b0 H
b0 `
11
02
b11111111111111111111111111110000 4
b11111111111111111111111111110000 ]
b11111111111111111111111111110000 c
b1100111001000000000000000100 :
b0 T
b11001 U
b1 a
b1 F
b1000 G
b11001 Z
b11001 Y
b100011001110010000000000000001 !
b100011001110010000000000000001 *
b100011001110010000000000000001 ,
b100011001110010000000000000001 M
b10000 ?
b1100 #
b1100 (
b1100 5
b1100 L
b1100 X
1%
#40000
0%
#45000
b10100 A
b10100 P
b10100 d
b11111111111111111111111111101100 /
b11111111111111111111111111101100 R
b11111111111111111111111111101100 \
b10100 +
b10100 W
b10100 0
b10100 N
b10000 .
b10000 V
b10000 [
1>
11
1B
b11111111111111111111111111101100 "
b11111111111111111111111111101100 )
b11111111111111111111111111101100 C
b11111111111111111111111111101100 J
b11111111111111111111111111101100 S
b11111111111111111111111111101100 f
b10000000000000001010000 :
b10000 U
b10100 a
b10100 F
b10000 Z
b0 Y
b0 3
b0 I
b0 O
b0 ^
b0 4
b0 ]
b0 c
b100000000100000000000000010100 !
b100000000100000000000000010100 *
b100000000100000000000000010100 ,
b100000000100000000000000010100 M
b1100000 ?
b10000 #
b10000 (
b10000 5
b10000 L
b10000 X
1%
#50000
0%
#55000
b11111111111111111111111111110001 /
b11111111111111111111111111110001 R
b11111111111111111111111111110001 \
b11111111111111111111111111110001 "
b11111111111111111111111111110001 )
b11111111111111111111111111110001 C
b11111111111111111111111111110001 J
b11111111111111111111111111110001 S
b11111111111111111111111111110001 f
b1111 A
b1111 P
b1111 d
b11000 +
b11000 W
b1111 0
b1111 N
b10001 .
b10001 V
b10001 [
1>
11
1B
b10001000000000000111100 :
b10001 U
b1111 a
b1111 F
b10001 Z
b100000000100010000000000001111 !
b100000000100010000000000001111 *
b100000000100010000000000001111 ,
b100000000100010000000000001111 M
b0 3
b0 I
b0 O
b0 ^
b1010000 ?
b10100 #
b10100 (
b10100 5
b10100 L
b10100 X
1%
#60000
0%
#65000
b11111111111111111111111111011101 /
b11111111111111111111111111011101 R
b11111111111111111111111111011101 \
b1000 .
b1000 V
b1000 [
b11111111111111111111111111110001 A
b11111111111111111111111111110001 P
b11111111111111111111111111110001 d
b11111111111111111111111111011101 "
b11111111111111111111111111011101 )
b11111111111111111111111111011101 C
b11111111111111111111111111011101 J
b11111111111111111111111111011101 S
b11111111111111111111111111011101 f
b11100 +
b11100 W
b100000000100000 0
b100000000100000 N
b1 E
b1 b
b1 e
b10 D
b10 H
b10 `
12
0>
11
0B
b11111111111111111111111111101100 4
b11111111111111111111111111101100 ]
b11111111111111111111111111101100 c
b1000010001010000000010000000 :
b1000 T
b100000 a
b100000 F
b0 G
b10000 Y
b11111111111111111111111111110001 3
b11111111111111111111111111110001 I
b11111111111111111111111111110001 O
b11111111111111111111111111110001 ^
b10000100010100000000100000 !
b10000100010100000000100000 *
b10000100010100000000100000 ,
b10000100010100000000100000 M
b10000000010011000 ?
b11000 #
b11000 (
b11000 5
b11000 L
b11000 X
1%
#70000
0%
#75000
b11111111111111111111111111111011 /
b11111111111111111111111111111011 R
b11111111111111111111111111111011 \
b11111111111111111111111111111011 "
b11111111111111111111111111111011 )
b11111111111111111111111111111011 C
b11111111111111111111111111111011 J
b11111111111111111111111111111011 S
b11111111111111111111111111111011 f
b100000 +
b100000 W
b100100000100010 0
b100100000100010 N
b1001 .
b1001 V
b1001 [
b10 E
b10 b
b10 e
b10 D
b10 H
b10 `
11
12
b1000010001010010000010001000 :
b1001 T
b100010 a
b100010 F
b10000100010100100000100010 !
b10000100010100100000100010 *
b10000100010100100000100010 ,
b10000100010100100000100010 M
b10010000010100100 ?
b11100 #
b11100 (
b11100 5
b11100 L
b11100 X
1%
#80000
0%
#85000
b11111111111111111111111111011000 /
b11111111111111111111111111011000 R
b11111111111111111111111111011000 \
b11111111111111111111111111011000 "
b11111111111111111111111111011000 )
b11111111111111111111111111011000 C
b11111111111111111111111111011000 J
b11111111111111111111111111011000 S
b11111111111111111111111111011000 f
b10100 A
b10100 P
b10100 d
b100100 +
b100100 W
b10100 0
b10100 N
b1010 .
b1010 V
b1010 [
1>
1B
b0 D
b0 H
b0 `
11
02
b0 3
b0 I
b0 O
b0 ^
b1000001010000000000001010000 :
b0 T
b1010 U
b10100 a
b10100 F
b1000 G
b1010 Z
b100010000010100000000000010100 !
b100010000010100000000000010100 *
b100010000010100000000000010100 ,
b100010000010100000000000010100 M
b1110000 ?
b100000 #
b100000 (
b100000 5
b100000 L
b100000 X
1%
#90000
0%
#95000
b11111111111111111111111111100000 /
b11111111111111111111111111100000 R
b11111111111111111111111111100000 \
b11111111111111111111111111100000 "
b11111111111111111111111111100000 )
b11111111111111111111111111100000 C
b11111111111111111111111111100000 J
b11111111111111111111111111100000 S
b11111111111111111111111111100000 f
b11111111111111111111111111110001 A
b11111111111111111111111111110001 P
b11111111111111111111111111110001 d
b101000 +
b101000 W
b101100000100100 0
b101100000100100 N
b1011 .
b1011 V
b1011 [
b11 E
b11 b
b11 e
b10 D
b10 H
b10 `
12
0>
11
0B
b1000010001010110000010010000 :
b1011 T
b10001 U
b100100 a
b100100 F
b0 G
b10001 Z
b10000100010101100000100100 !
b10000100010101100000100100 *
b10000100010101100000100100 ,
b10000100010101100000100100 M
b11111111111111111111111111110001 3
b11111111111111111111111111110001 I
b11111111111111111111111111110001 O
b11111111111111111111111111110001 ^
b10110000010110100 ?
b100100 #
b100100 (
b100100 5
b100100 L
b100100 X
1%
#100000
0%
#105000
b11111111111111111111111111111101 /
b11111111111111111111111111111101 R
b11111111111111111111111111111101 \
b11111111111111111111111111111101 "
b11111111111111111111111111111101 )
b11111111111111111111111111111101 C
b11111111111111111111111111111101 J
b11111111111111111111111111111101 S
b11111111111111111111111111111101 f
b101100 +
b101100 W
b110000000100101 0
b110000000100101 N
b1100 .
b1100 V
b1100 [
b100 E
b100 b
b100 e
b10 D
b10 H
b10 `
11
12
b1000010001011000000010010100 :
b1100 T
b100101 a
b100101 F
b10000100010110000000100101 !
b10000100010110000000100101 *
b10000100010110000000100101 ,
b10000100010110000000100101 M
b11000000010111100 ?
b101000 #
b101000 (
b101000 5
b101000 L
b101000 X
1%
#110000
0%
#115000
b11101 /
b11101 R
b11101 \
b11101 "
b11101 )
b11101 C
b11101 J
b11101 S
b11101 f
b110000 +
b110000 W
b110100000100110 0
b110100000100110 N
b1101 .
b1101 V
b1101 [
b101 E
b101 b
b101 e
b10 D
b10 H
b10 `
11
12
b1000010001011010000010011000 :
b1101 T
b100110 a
b100110 F
b10000100010110100000100110 !
b10000100010110100000100110 *
b10000100010110100000100110 ,
b10000100010110100000100110 M
b11010000011000100 ?
b101100 #
b101100 (
b101100 5
b101100 L
b101100 X
1%
#120000
0%
#125000
b10011 /
b10011 R
b10011 \
b10011 "
b10011 )
b10011 C
b10011 J
b10011 S
b10011 f
b110100 +
b110100 W
b111000000100111 0
b111000000100111 N
b1110 .
b1110 V
b1110 [
b110 E
b110 b
b110 e
b10 D
b10 H
b10 `
11
12
b1000010001011100000010011100 :
b1110 T
b100111 a
b100111 F
b10000100010111000000100111 !
b10000100010111000000100111 *
b10000100010111000000100111 ,
b10000100010111000000100111 M
b11100000011001100 ?
b110000 #
b110000 (
b110000 5
b110000 L
b110000 X
1%
#130000
0%
#135000
b11111111111111111111111111101110 /
b11111111111111111111111111101110 R
b11111111111111111111111111101110 \
b1 A
b1 P
b1 d
b11111111111111111111111111101110 "
b11111111111111111111111111101110 )
b11111111111111111111111111101110 C
b11111111111111111111111111101110 J
b11111111111111111111111111101110 S
b11111111111111111111111111101110 f
b111000 +
b111000 W
b1 0
b1 N
b11001 .
b11001 V
b11001 [
b10 E
b10 b
b10 e
1>
1B
b0 D
b0 H
b0 `
11
02
b11111111111111111111111111101111 3
b11111111111111111111111111101111 I
b11111111111111111111111111101111 O
b11111111111111111111111111101111 ^
b11111111111111111111111111101111 4
b11111111111111111111111111101111 ]
b11111111111111111111111111101111 c
b1100111001000000000000000100 :
b0 T
b11001 U
b1 a
b1 F
b1000 G
b11001 Z
b11001 Y
b100011001110010000000000000001 !
b100011001110010000000000000001 *
b100011001110010000000000000001 ,
b100011001110010000000000000001 M
b111000 ?
b110100 #
b110100 (
b110100 5
b110100 L
b110100 X
1%
#140000
0%
